dm_gcp/_tfhelper.cpython-38-x86_64-linux-gnu.so
dm_gcp/_switch_traffic.cpython-38-x86_64-linux-gnu.so
dm_gcp/gcplib.cpython-38-x86_64-linux-gnu.so
dm_gcp/discovery.py
dm_gcp/__init__.cpython-38-x86_64-linux-gnu.so
dm_gcp/_discovery.cpython-38-x86_64-linux-gnu.so
dm_gcp/switchlib.cpython-38-x86_64-linux-gnu.so
dm_gcp/exceptions.cpython-38-x86_64-linux-gnu.so
dm_gcp/tfhelper.py
dm_gcp/aviatrix.cpython-38-x86_64-linux-gnu.so
dm_gcp/terraform.cpython-38-x86_64-linux-gnu.so
dm_gcp/logconf.cpython-38-x86_64-linux-gnu.so
dm_gcp/commonlib.cpython-38-x86_64-linux-gnu.so
dm_gcp/switch_traffic.py
dm_gcp/res/__init__.cpython-38-x86_64-linux-gnu.so
dm_gcp/res/Globals.cpython-38-x86_64-linux-gnu.so
dm_gcp/res/RouteInfo.cpython-38-x86_64-linux-gnu.so
dm_gcp/res/AviatrixProviderVersion.cpython-38-x86_64-linux-gnu.so
dm_gcp/core/AvtxCidrValidator.cpython-38-x86_64-linux-gnu.so
dm_gcp/core/YamlContext.cpython-38-x86_64-linux-gnu.so
dm_gcp/core/__init__.cpython-38-x86_64-linux-gnu.so
dm_gcp/core/config.py
dm_gcp/core/Handler.cpython-38-x86_64-linux-gnu.so
dm_gcp/core/AppExitStatus.cpython-38-x86_64-linux-gnu.so
dm_gcp/core/ErrorStatusHandler.cpython-38-x86_64-linux-gnu.so
dm_gcp/template/providers.tf
dm_gcp/template/__init__.cpython-38-x86_64-linux-gnu.so
dm_gcp/template/terraform.tfvars
dm_gcp/template/variables.tf
dm_gcp/template/vpc_id.tf
dm_gcp/template/versions.tf
dm_gcp/template/module/__init__.cpython-38-x86_64-linux-gnu.so
dm_gcp/template/module/main.tf
dm_gcp/template/module/variables.tf
dm_gcp/template/module/versions.tf
aviatrix_migration_gcp-0.3.2.dist-info/RECORD
aviatrix_migration_gcp-0.3.2.dist-info/top_level.txt
aviatrix_migration_gcp-0.3.2.dist-info/METADATA
aviatrix_migration_gcp-0.3.2.dist-info/WHEEL
