Metadata-Version: 2.1
Name: aviatrix-migration-gcp
Version: 0.3.2
Requires-Dist: boto3==1.26.21
Requires-Dist: botocore==1.29.21
Requires-Dist: cachetools==5.2.0
Requires-Dist: certifi==2022.9.24
Requires-Dist: charset-normalizer==2.1.1
Requires-Dist: google-api-core==2.10.2
Requires-Dist: google-api-python-client==2.66.0
Requires-Dist: google-auth==2.14.1
Requires-Dist: google-auth-httplib2==0.1.0
Requires-Dist: google-cloud-compute==1.6.1
Requires-Dist: google-cloud-network-management==1.5.4
Requires-Dist: googleapis-common-protos==1.57.0
Requires-Dist: grpcio==1.50.0
Requires-Dist: grpcio-status==1.50.0
Requires-Dist: httplib2==0.21.0
Requires-Dist: idna==3.4
Requires-Dist: Jinja2==3.0.3
Requires-Dist: jmespath==1.0.1
Requires-Dist: MarkupSafe==2.1.2
Requires-Dist: oauth2client==4.1.3
Requires-Dist: packaging==21.3
Requires-Dist: proto-plus==1.22.1
Requires-Dist: protobuf==4.21.9
Requires-Dist: pyasn1==0.4.8
Requires-Dist: pyasn1-modules==0.2.8
Requires-Dist: pydantic==1.9.0
Requires-Dist: pyparsing==3.0.9
Requires-Dist: python-dateutil==2.8.2
Requires-Dist: PyYAML==6.0.2
Requires-Dist: requests==2.28.1
Requires-Dist: retry==0.9.2
Requires-Dist: rsa==4.9
Requires-Dist: s3transfer==0.6.0
Requires-Dist: six==1.16.0
Requires-Dist: typing-extensions==4.4.0
Requires-Dist: uritemplate==4.1.1
Requires-Dist: urllib3==1.26.13
